ukraine/__init__.py
ukraine/agents/complex.py
ukraine/agents/rag.py
ukraine/research/experimental.py
ukraine/research/expressnet/layers.py
ukraine/research/expressnet/model.py
ukraine/research/phaseunet/inference.py
ukraine/research/phaseunet/model.py
ukraine/research/phaseunet/utils.py
ukraine/research/synthia/layers.py
ukraine/research/synthia/losses.py
ukraine/research/synthia/model.py
ukraine/research/transformer/layers.py
ukraine/research/transformer/masking.py
ukraine/research/transformer/tokenizers.py
ukraine/research/transformer/transformer.py
ukraine-0.4.0.dist-info/METADATA
ukraine-0.4.0.dist-info/WHEEL
ukraine-0.4.0.dist-info/top_level.txt
ukraine-0.4.0.dist-info/RECORD
