Metadata-Version: 2.4
Name: ukraine
Version: 0.4.0
Summary: Ukraine: A Data Science Toolkit
Author-email: Anar <anarstanislavlavrenov@gmail.com>
License: MIT
Requires-Python: >=3.7
Provides-Extra: langchain-openai
Requires-Dist: langchain-openai; extra == "langchain-openai"
Requires-Dist: langchain_community; extra == "langchain-openai"
Requires-Dist: pypdf; extra == "langchain-openai"
Requires-Dist: faiss-cpu; extra == "langchain-openai"
Provides-Extra: langchain-deepseek
Requires-Dist: langchain-deepseek; extra == "langchain-deepseek"
Requires-Dist: langchain_community; extra == "langchain-deepseek"
Requires-Dist: langchain_openai; extra == "langchain-deepseek"
Requires-Dist: pypdf; extra == "langchain-deepseek"
Requires-Dist: faiss-cpu; extra == "langchain-deepseek"
Provides-Extra: langchain-llama
Requires-Dist: langchain-nvidia-ai-endpoints; extra == "langchain-llama"
Requires-Dist: langchain_community; extra == "langchain-llama"
Requires-Dist: langchain_openai; extra == "langchain-llama"
Requires-Dist: pypdf; extra == "langchain-llama"
Requires-Dist: faiss-cpu; extra == "langchain-llama"
Provides-Extra: jira
Requires-Dist: langchain-openai; extra == "jira"
Requires-Dist: langchain_community; extra == "jira"
Requires-Dist: langchain; extra == "jira"
Requires-Dist: atlassian-python-api; extra == "jira"
Provides-Extra: agno
Requires-Dist: agno; extra == "agno"
Requires-Dist: firecrawl; extra == "agno"
Provides-Extra: expressnet
Requires-Dist: torch; extra == "expressnet"
Provides-Extra: phaseunet
Requires-Dist: torch; extra == "phaseunet"
Requires-Dist: torchaudio; extra == "phaseunet"
